dspy/__init__.py
dspy/data_preparation.py
dspy/data_understanding.py
dspy/deployment.py
dspy/evaluation.py
dspy/modeling.py
dsmlpy-0.0.1.dist-info/METADATA
dsmlpy-0.0.1.dist-info/WHEEL
dsmlpy-0.0.1.dist-info/top_level.txt
dsmlpy-0.0.1.dist-info/RECORD
